tests/__init__.py
tests/context.py
tests/cells/__init__.py
tests/cells/test_pcell_basic.py
tests/cells/test_pcell_library.py
tests/cells/test_pcell_params.py
tests/layout/__init__.py
tests/layout/test_cache.py
tests/layout/test_layout_write.py
tests/layout/test_metadata.py
tests/layout/test_points.py
tests/layout/test_rectangle.py
tests/layout/test_waveguide.py
tests/technology/__init__.py
tests/technology/test_basic.py
tests/technology/test_xml.py
zeropdk/__init__.py
zeropdk/exceptions.py
zeropdk/pcell.py
zeropdk/default_library/__init__.py
zeropdk/default_library/io.py
zeropdk/klayout_extend/__init__.py
zeropdk/klayout_extend/cell.py
zeropdk/klayout_extend/layout.py
zeropdk/klayout_extend/point.py
zeropdk/klayout_extend/polygon.py
zeropdk/layout/__init__.py
zeropdk/layout/bezier_optimal.npz
zeropdk/layout/cache.py
zeropdk/layout/geometry.py
zeropdk/layout/polygons.py
zeropdk/layout/routing.py
zeropdk/layout/waveguide_rounding.py
zeropdk/layout/waveguides.py
zeropdk/layout/algorithms/__init__.py
zeropdk/layout/algorithms/sampling.py
zeropdk/tech/__init__.py
zeropdk-22.8.dist-info/LICENSE
zeropdk-22.8.dist-info/METADATA
zeropdk-22.8.dist-info/WHEEL
zeropdk-22.8.dist-info/top_level.txt
zeropdk-22.8.dist-info/RECORD
