Metadata-Version: 2.1
Name: zeropdk
Version: 22.8
Summary: PDK factory for klayout
Home-page: https://github.com/lightwave-lab/zeropdk
Author: Thomas Ferreira de Lima <tlima@princeton.edu>
Author-email: tlima@princeton.edu
License: MIT License
Classifier: Programming Language :: Python :: 3.6
Classifier: Programming Language :: Python :: 3.7
Classifier: License :: OSI Approved :: MIT License
Classifier: Operating System :: OS Independent
Classifier: Topic :: Scientific/Engineering
Requires-Python: >=3.7
License-File: LICENSE
Requires-Dist: numpy
Requires-Dist: klayout
Requires-Dist: scipy
